<?xml version='1.0' encoding='windows-1252' ?>
<!DOCTYPE ViewObject SYSTEM "jbo_03_01.dtd">

<ViewObject
   Name="xxCactBankLatestTxn"
   BindingStyle="OracleName"
   CustomQuery="true"
   RowClass="oracle.apps.fnd.framework.server.OAViewRowImpl"
   ComponentClass="xxfinalcactbank.oracle.apps.fnd.cactbank.server.xxCactBankLatestTxnImpl"
   UseGlueCode="false" >
   <SQLQuery><![CDATA[
select txn.ACC_NO, txn.ACC_HOLDER_NAME, txn.TRANSFER_ACC_NO, case when (txn.TRANSFER_ACC_NO is not null) then txn.amount else 0 end CREDIT, CASE when (txn.TRANSFER_ACC_NO is null) then txn.amount else 0 end Debit, bnk.balance  from xxcact_TRANSACTION txn, xxcact_BANK bnk
where txn.acc_no=BNK.ACC_NO
   ]]></SQLQuery>
   <DesignTime>
      <Attr Name="_isExpertMode" Value="true" />
      <Attr Name="_version" Value="10.1.3.41.57" />
      <Attr Name="_codeGenFlag2" Value="Access|Coll|VarAccess" />
   </DesignTime>
   <ViewAttribute
      Name="AccNo"
      IsPersistent="false"
      Type="oracle.jbo.domain.Number"
      ColumnType="NUMBER"
      AliasName="ACC_NO"
      Expression="ACC_NO"
      SQLType="NUMERIC" >
      <DesignTime>
         <Attr Name="_DisplaySize" Value="22" />
      </DesignTime>
   </ViewAttribute>
   <ViewAttribute
      Name="AccHolderName"
      IsPersistent="false"
      Precision="30"
      Type="java.lang.String"
      ColumnType="VARCHAR2"
      AliasName="ACC_HOLDER_NAME"
      Expression="ACC_HOLDER_NAME"
      SQLType="VARCHAR" >
      <DesignTime>
         <Attr Name="_DisplaySize" Value="30" />
      </DesignTime>
   </ViewAttribute>
   <ViewAttribute
      Name="TransferAccNo"
      IsPersistent="false"
      Type="oracle.jbo.domain.Number"
      ColumnType="NUMBER"
      AliasName="TRANSFER_ACC_NO"
      Expression="TRANSFER_ACC_NO"
      SQLType="NUMERIC" >
      <DesignTime>
         <Attr Name="_DisplaySize" Value="22" />
      </DesignTime>
   </ViewAttribute>
   <ViewAttribute
      Name="Credit"
      IsPersistent="false"
      Type="oracle.jbo.domain.Number"
      ColumnType="NUMBER"
      AliasName="CREDIT"
      Expression="CREDIT"
      SQLType="NUMERIC" >
      <DesignTime>
         <Attr Name="_DisplaySize" Value="22" />
      </DesignTime>
   </ViewAttribute>
   <ViewAttribute
      Name="Debit"
      IsPersistent="false"
      Type="oracle.jbo.domain.Number"
      ColumnType="NUMBER"
      AliasName="DEBIT"
      Expression="DEBIT"
      SQLType="NUMERIC" >
      <DesignTime>
         <Attr Name="_DisplaySize" Value="22" />
      </DesignTime>
   </ViewAttribute>
   <ViewAttribute
      Name="Balance"
      IsPersistent="false"
      Type="oracle.jbo.domain.Number"
      ColumnType="NUMBER"
      AliasName="BALANCE"
      Expression="BALANCE"
      SQLType="NUMERIC" >
      <DesignTime>
         <Attr Name="_DisplaySize" Value="22" />
      </DesignTime>
   </ViewAttribute>
</ViewObject>
